{
  "users": [
    {
      "id": 1,
      "name": "Dewansh2",
      "age": 28
    },
    {
      "name": "myname",
      "age": 20,
      "id": 2
    },
    {
      "id": 3
    },
    {
      "name": "myname",
      "age": 20,
      "id": 4
    },
    {
      "name": "Dewa",
      "age": 27,
      "id": 5
    },
    {
      "name": "Dewansh3",
      "age": 28,
      "id": 6
    },
    {
      "name": "Dewans",
      "age": 20,
      "id": 7
    },
    {
      "name": "Hello Dewansh",
      "age": 20,
      "id": 8
    }
  ]
}